tri_buf.v
module tri_buf(a, b, enable);
    input [15:0] a; //bits based on in and out
    input enable;
    output reg [15:0] b;

    always @(enable or a) begin
        if  (enable) begin
            b = a;
        end else begin
            b = 3'bzzz;
        end
    end

endmodule

register.v
module register(x, clk, enable, y);
    //4-bit register
    //given in lecture 10 - modified
    input [15:0] x;
    input clk, enable;
    output reg [15:0] y;

    always @(clk or  enable) begin
        if (enable == 1'b1)
            y <= x; 
        
    end

endmodule

divide.v
module divide (dividend, divisor, quotient, remainder);
    input [15:0] dividend, divisor;
    output [15:0] quotient, remainder;
    
    assign quotient = dividend/divisor;
    assign remainder = dividend%divisor;

endmodule

or_function.v
module or_function(a, b, g);
    input [15:0] a, b;
    output [15:0] g;

    assign g = a | b;

endmodule

and_function.v
module and_function (a, b, g);
    input [15:0] a, b;
    output [15:0] g;
    
    assign g = a & b;
endmodule

subbing.v
module subbing(a,b,out);
    input [15:0] a, b;
    output [15:0] out;

    assign out = a-b;

endmodule

adding.v
module adding(a, b, out,  addsub);
    input [15:0] a, b;
    input addsub;
    output [15:0] out;

    wire temp;
    wire t;
    assign t = 1'b0;
    assign out = a+b;
    //fourBit_FA pls(.a(a),.b(b),.cin(t),.cout(temp),.s(out));
    
endmodule

xor_function.v
module xor_function (a, b, g);
	input [15:0] a, b;
	output [15:0] g;
	
	assign g = a ^ b;

endmodule

my_alu.v
module my_alu(p, q, math_out, g);
    input [15:0] p, q;
	input [6:0] math_out;
	output [15:0] g;
	wire [15:0] xor_out, add_out, sub_out, and_out, or_out, divide_out, mod_out;
	


	xor_function my_xor(.a(p), .b(q), .g(xor_out));
	tri_buf xortri(.a(xor_out), .enable(math_out[6]), .b(g));

	adding addme(.a(p), .b(q), .addsub(AddSub), .out(add_out));
	tri_buf addtri(.a(add_out), .enable(math_out[5]), .b(g));

	subbing subme(.a(p), .b(q), .out(sub_out));
	tri_buf subtri(.a(sub_out), .enable(math_out[4]), .b(g));

	and_function andme(.a(p), .b(q), .g(and_out));
	tri_buf andtri(.a(and_out), .enable(math_out[3]), .b(g));

	or_function orme(.a(p), .b(q), .g(or_out));
	tri_buf ortri(.a(or_out), .enable(math_out[2]), .b(g));

	divide divme(.dividend(p), .divisor(q), .quotient(divide_out), .remainder(mod_out));
	tri_buf divtri(.a(divide_out), .enable(math_out[1]), .b(g));
	tri_buf modtri(.a(mod_out), .enable(math_out[0]), .b(g));

 
endmodule

reg_decoder.v
module reg_decoder(reg_num, clk, reg_enable);
    input clk;
    input [15:0] reg_num;
    output reg [7:0] reg_enable; //8 registers

    always @(clk) begin
        case(reg_num)
            16'h000 : reg_enable = 8'b10000000; 
            16'h001 : reg_enable = 8'b01000000;
            16'h002 : reg_enable = 8'b00100000;
            16'h003 : reg_enable = 8'b00010000;
            16'h004 : reg_enable = 8'b00001000; 
            16'h005 : reg_enable = 8'b00000100;
            16'h006 : reg_enable = 8'b00000010;
            16'h007 : reg_enable = 8'b00000001;
            default : reg_enable = 8'b00000000; 
        endcase
    end
endmodule

my_fsm.v
module my_fsm (input1, input2, current_state, func, clk, next_state, data_out, R_in, R_out, AddSub, a_in, g_in, g_out,  math_enables);
    input clk;
    input [15:0] input1, input2;
    input [3:0] func;
    input [4:0] current_state; 
    output reg [4:0] next_state;
    output reg data_out, AddSub,a_in, g_in, g_out;
    output reg [7:0] R_out, R_in;
    wire [7:0] temp1, temp2;
    wire [8:0] temp;
    output reg [6:0] math_enables; // [xor, add, sub, and, or, divide, modulo]

    
    assign temp = {func, current_state};

    reg_decoder in1(.reg_num(input1), .clk(clk), .reg_enable(temp1));
    reg_decoder in2(.reg_num(input2), .clk(clk), .reg_enable(temp2));

 


    always @ (clk) begin
        case(temp)
            //load
            9'b000100000 : begin next_state = 5'b00001; data_out = 1'b1; R_in = temp1; R_out <= 8'b00000000; AddSub = 1'b0; a_in = 1'b0;   g_in = 1'b0; g_out = 1'b0; end
            //move
            9'b001000000 : begin next_state = 5'b00010; data_out = 1'b0; R_in = temp1; R_out = temp2;  AddSub = 1'b0; a_in = 1'b0;   g_in = 1'b0; g_out = 1'b0; end
            //add
            9'b001100000 : begin next_state = 5'b00011; data_out = 1'b0; R_in <= 8'b00000000; R_out = temp1;  AddSub = 1'b0; a_in = 1'b1;   g_in = 1'b0; g_out = 1'b0; math_enables = 7'b0100000; end
            9'b001100011 : begin next_state = 5'b00100; data_out = 1'b0; R_in <= 8'b00000000;R_out = temp2;  AddSub = 1'b0; a_in = 1'b1;   g_in = 1'b1; g_out = 1'b0; math_enables = 7'b0100000; end
            9'b001100100 : begin next_state = 5'b00101; data_out = 1'b0; R_in = temp1; R_out <= 8'b00000000; AddSub = 1'b0; a_in = 1'b0;   g_in = 1'b1; g_out = 1'b1; math_enables = 7'b0100000; end
            //subtract
            9'b010000000 : begin next_state = 5'b00111; data_out = 1'b0; R_in <= 8'b00000000;R_out = temp1;  AddSub = 1'b1; a_in = 1'b1;   g_in = 1'b0; g_out = 1'b0; math_enables = 7'b0010000; end
            9'b010000111 : begin next_state = 5'b01000; data_out = 1'b0; R_in <= 8'b00000000;R_out = temp2;  AddSub = 1'b1; a_in = 1'b1;   g_in = 1'b1; g_out = 1'b0; math_enables = 7'b0010000; end
            9'b010001000 : begin next_state = 5'b01001; data_out = 1'b0; R_in = temp1; R_out <= 8'b00000000; AddSub = 1'b1; a_in = 1'b0;   g_in = 1'b1; g_out = 1'b1; math_enables = 7'b0010000; end
            //xor
            9'b010100000 : begin next_state = 5'b01010; data_out = 1'b0; R_in <= 8'b00000000;R_out = temp1;  AddSub = 1'b0; a_in = 1'b1;   g_in = 1'b0; g_out = 1'b0; math_enables = 7'b1000000; end
            9'b010101010 : begin next_state = 5'b01011; data_out = 1'b0; R_in <= 8'b00000000;R_out = temp2;  AddSub = 1'b0; a_in = 1'b1;   g_in = 1'b1; g_out = 1'b0; math_enables = 7'b1000000; end
            9'b010101011 : begin next_state = 5'b01100; data_out = 1'b0; R_in = temp1 ;R_out = 8'b00000000; AddSub = 1'b0; a_in = 1'b0;  g_in = 1'b1; g_out = 1'b1; math_enables = 7'b1000000; end
            //or
            9'b011000000 : begin next_state = 5'b01101; data_out = 1'b0; R_in <= 8'b00000000; R_out = temp1; AddSub = 1'b0; a_in = 1'b1; g_in = 1'b0; g_out = 1'b0; math_enables = 7'b0000100; end
            9'b011001101 : begin next_state = 5'b01110; data_out = 1'b0; R_in <= 8'b00000000; R_out = temp2;  AddSub = 1'b0; a_in = 1'b1;   g_in = 1'b1; g_out = 1'b0; math_enables = 7'b0000100; end
            9'b011001110 : begin next_state = 5'b01111; data_out = 1'b0; R_in = temp1; R_out = 8'b00000000; AddSub = 1'b0; a_in = 1'b0;  g_in = 1'b1; g_out = 1'b1; math_enables = 7'b0000100; end
            //and
            9'b011100000 : begin next_state = 5'b10000; data_out = 1'b0; R_in <= 8'b00000000; R_out = temp1; AddSub = 1'b0; a_in = 1'b1; g_in = 1'b0; g_out = 1'b0; math_enables = 7'b0001000; end
            9'b011110000 : begin next_state = 5'b10001; data_out = 1'b0; R_in <= 8'b00000000 ;R_out = temp2;  AddSub = 1'b0; a_in = 1'b1;   g_in = 1'b1; g_out = 1'b0; math_enables = 7'b0001000; end
            9'b011110001 : begin next_state = 5'b10010; data_out = 1'b0; R_in = temp1 ;R_out = 8'b00000000; AddSub = 1'b0; a_in = 1'b0;  g_in = 1'b1; g_out = 1'b1; math_enables = 7'b0001000; end
            //divide
            9'b100000000 : begin next_state = 5'b10011; data_out = 1'b0; R_in <= 8'b00000000; R_out = temp1; AddSub = 1'b0; a_in = 1'b1; g_in = 1'b0; g_out = 1'b0; math_enables = 7'b0000010; end
            9'b100010011 : begin next_state = 5'b10100; data_out = 1'b0; R_in <= 8'b00000000 ;R_out = temp2;  AddSub = 1'b0; a_in = 1'b1;   g_in = 1'b1; g_out = 1'b0; math_enables = 7'b0000010; end
            9'b100010100 : begin next_state = 5'b10101; data_out = 1'b0; R_in = temp1 ;R_out = 8'b00000000; AddSub = 1'b0; a_in = 1'b0;  g_in = 1'b1; g_out = 1'b1; math_enables = 7'b0000010; end
            //modulo
            9'b100100000 : begin next_state = 5'b10110; data_out = 1'b0; R_in <= 8'b00000000; R_out = temp1; AddSub = 1'b0; a_in = 1'b1; g_in = 1'b0; g_out = 1'b0; math_enables = 7'b0000001; end
            9'b100110110 : begin next_state = 5'b10111; data_out = 1'b0; R_in <= 8'b00000000 ;R_out = temp2;  AddSub = 1'b0; a_in = 1'b1;   g_in = 1'b1; g_out = 1'b0; math_enables = 7'b0000001; end
            9'b100110111 : begin next_state = 5'b11000; data_out = 1'b0; R_in = temp1 ;R_out = 8'b00000000; AddSub = 1'b0; a_in = 1'b0;  g_in = 1'b1; g_out = 1'b1; math_enables = 7'b0000001; end
            default begin next_state = 5'b00000; data_out = 1'b0; R_in <= 8'b00000000;R_out <= 8'b00000000; AddSub = 1'b0; a_in = 1'b0;   g_in = 1'b0; g_out = 1'b0; math_enables = 7'b0000000; end
        endcase
    end
endmodule

load_TB.v
`timescale 1ns / 1ps
 
module mod_TB;
 
	reg [15:0] in1, in2;
	wire [15:0] bus, t0, t1, t2, t3, t4, t5, t6, t7, t8, temp, a_out, temp1, alu_out,  xor_out, add_out, sub_out, g;
	wire [2:0] and_out, or_out, divide_out, mod_out;
	reg clk;
	reg [3:0] func;
	wire data_out, a_in, g_out, g_in,  AddSub, AS_enable, XOR_enable;
	reg [4:0] count;
	wire [7:0] reg_in, reg_out;
	wire [4:0] current_state;
	wire [6:0] math_out;

	

	my_fsm cc(.current_state(current_state), .input1(in1), .input2(in2), .func(func), .clk(clk), .next_state(current_state), .data_out(data_out), .R_in(reg_in), .R_out(reg_out), .AddSub(AddSub), .a_in(a_in), .g_in(g_in), .g_out(g_out), .math_enables(math_out));

	//registers
	tri_buf D(.a(in2), .enable(data_out), .b(bus));

	register R0(.x(bus), .clk(clk), .enable(reg_in[7]), .y(t0));
	register R1(.x(bus), .clk(clk), .enable(reg_in[6]), .y(t1));
	register R2(.x(bus), .clk(clk), .enable(reg_in[5]), .y(t2));
	register R3(.x(bus), .clk(clk), .enable(reg_in[4]), .y(t3));
	register R4(.x(bus), .clk(clk), .enable(reg_in[3]), .y(t4));
	register R5(.x(bus), .clk(clk), .enable(reg_in[2]), .y(t5));
	register R6(.x(bus), .clk(clk), .enable(reg_in[1]), .y(t6));
	register R7(.x(bus), .clk(clk), .enable(reg_in[0]), .y(t7));


	tri_buf T0(.a(t0), .enable(reg_out[7]), .b(bus));
	tri_buf T1(.a(t1), .enable(reg_out[6]), .b(bus));
	tri_buf T2(.a(t2), .enable(reg_out[5]), .b(bus));
	tri_buf T3(.a(t3), .enable(reg_out[4]), .b(bus));
	tri_buf T4(.a(t4), .enable(reg_out[3]), .b(bus));
	tri_buf T5(.a(t5), .enable(reg_out[2]), .b(bus));
	tri_buf T6(.a(t6), .enable(reg_out[1]), .b(bus));
	tri_buf T7(.a(t7), .enable(reg_out[0]), .b(bus));

	register A(.x(bus), .clk(clk), .enable(a_in), .y(a_out));

	my_alu alu( .p(a_out), .q(bus), .math_out(math_out), .g(g));
	

	register G(.x(g), .clk(clk), .enable(g_in), .y(temp1));
	tri_buf g_buf(.a(temp1), .enable(g_out), .b(bus));
	
	initial begin 
		count = 5'b00000;
	end
	
	always begin
		#50
		count=count+5'b00001;
	end
	
	always @(count) begin
		case (count)
			5'b00000 : begin clk = 1; func = 4'b0001; in1 = 3'b000; in2 = 3'b101; end
			5'b00001 : begin clk = 0; end
			5'b00010 : begin clk = 1; func = 4'b0001; in1 = 3'b100; in2 = 3'b101; end
			5'b00011 : begin clk = 0; end
			5'b00100 : begin clk = 1; func = 4'b0001; in1 = 3'b010; in2 = 3'b100; end
			5'b00101 : begin clk = 0; end
			5'b00110 : begin clk = 1; func = 4'b0001; in1 = 3'b101; in2 = 3'b001; end
			5'b00111 : begin clk = 0; end
			5'b01000 : begin clk = 1; func = 4'b0010; in1 = 3'b000; in2 = 3'b101; end
			5'b01001 : begin clk = 0; end
			5'b01010 : begin clk = 1; func = 4'b0010; in1 = 3'b010; in2 = 3'b000; end
			5'b01011 : begin clk = 0; end
			5'b01100 : begin clk = 1; func = 4'b1001; in1 = 3'b000; in2 = 3'b101; end
			5'b01101 : begin clk = 0; end
			5'b01110 : begin clk = 1; func = 4'b1001; in1 = 3'b000; in2 = 3'b101; end
			5'b01111 : begin clk = 0; end
			5'b10000 : begin clk = 1; func = 4'b1001; in1 = 3'b000; in2 = 3'b101; end
			5'b10001 : begin clk = 0; end


		endcase
	end

	initial begin
		$dumpfile("mod_TB.vcd");
		$dumpvars(0, mod_TB);
		#1000
		$finish;
	end
 
endmodule

mod_TB.vcd
$date
	Tue May 23 17:39:27 2023
$end
$version
	Icarus Verilog
$end
$timescale
	1ps
$end
$scope module mod_TB $end
$var wire 16 ! bus [15:0] $end
$var wire 16 " g [15:0] $end
$var wire 16 # temp1 [15:0] $end
$var wire 16 $ t7 [15:0] $end
$var wire 16 % t6 [15:0] $end
$var wire 16 & t5 [15:0] $end
$var wire 16 ' t4 [15:0] $end
$var wire 16 ( t3 [15:0] $end
$var wire 16 ) t2 [15:0] $end
$var wire 16 * t1 [15:0] $end
$var wire 16 + t0 [15:0] $end
$var wire 8 , reg_out [7:0] $end
$var wire 8 - reg_in [7:0] $end
$var wire 7 . math_out [6:0] $end
$var wire 1 / g_out $end
$var wire 1 0 g_in $end
$var wire 1 1 data_out $end
$var wire 5 2 current_state [4:0] $end
$var wire 16 3 a_out [15:0] $end
$var wire 1 4 a_in $end
$var wire 1 5 AddSub $end
$var reg 1 6 clk $end
$var reg 5 7 count [4:0] $end
$var reg 4 8 func [3:0] $end
$var reg 16 9 in1 [15:0] $end
$var reg 16 : in2 [15:0] $end
$scope module A $end
$var wire 1 6 clk $end
$var wire 16 ; x [15:0] $end
$var wire 1 4 enable $end
$var reg 16 < y [15:0] $end
$upscope $end
$scope module D $end
$var wire 16 = a [15:0] $end
$var wire 1 1 enable $end
$var reg 16 > b [15:0] $end
$upscope $end
$scope module G $end
$var wire 1 6 clk $end
$var wire 16 ? x [15:0] $end
$var wire 1 0 enable $end
$var reg 16 @ y [15:0] $end
$upscope $end
$scope module R0 $end
$var wire 1 6 clk $end
$var wire 1 A enable $end
$var wire 16 B x [15:0] $end
$var reg 16 C y [15:0] $end
$upscope $end
$scope module R1 $end
$var wire 1 6 clk $end
$var wire 1 D enable $end
$var wire 16 E x [15:0] $end
$var reg 16 F y [15:0] $end
$upscope $end
$scope module R2 $end
$var wire 1 6 clk $end
$var wire 1 G enable $end
$var wire 16 H x [15:0] $end
$var reg 16 I y [15:0] $end
$upscope $end
$scope module R3 $end
$var wire 1 6 clk $end
$var wire 1 J enable $end
$var wire 16 K x [15:0] $end
$var reg 16 L y [15:0] $end
$upscope $end
$scope module R4 $end
$var wire 1 6 clk $end
$var wire 1 M enable $end
$var wire 16 N x [15:0] $end
$var reg 16 O y [15:0] $end
$upscope $end
$scope module R5 $end
$var wire 1 6 clk $end
$var wire 1 P enable $end
$var wire 16 Q x [15:0] $end
$var reg 16 R y [15:0] $end
$upscope $end
$scope module R6 $end
$var wire 1 6 clk $end
$var wire 1 S enable $end
$var wire 16 T x [15:0] $end
$var reg 16 U y [15:0] $end
$upscope $end
$scope module R7 $end
$var wire 1 6 clk $end
$var wire 1 V enable $end
$var wire 16 W x [15:0] $end
$var reg 16 X y [15:0] $end
$upscope $end
$scope module T0 $end
$var wire 16 Y a [15:0] $end
$var wire 1 Z enable $end
$var reg 16 [ b [15:0] $end
$upscope $end
$scope module T1 $end
$var wire 16 \ a [15:0] $end
$var wire 1 ] enable $end
$var reg 16 ^ b [15:0] $end
$upscope $end
$scope module T2 $end
$var wire 16 _ a [15:0] $end
$var wire 1 ` enable $end
$var reg 16 a b [15:0] $end
$upscope $end
$scope module T3 $end
$var wire 16 b a [15:0] $end
$var wire 1 c enable $end
$var reg 16 d b [15:0] $end
$upscope $end
$scope module T4 $end
$var wire 16 e a [15:0] $end
$var wire 1 f enable $end
$var reg 16 g b [15:0] $end
$upscope $end
$scope module T5 $end
$var wire 16 h a [15:0] $end
$var wire 1 i enable $end
$var reg 16 j b [15:0] $end
$upscope $end
$scope module T6 $end
$var wire 16 k a [15:0] $end
$var wire 1 l enable $end
$var reg 16 m b [15:0] $end
$upscope $end
$scope module T7 $end
$var wire 16 n a [15:0] $end
$var wire 1 o enable $end
$var reg 16 p b [15:0] $end
$upscope $end
$scope module alu $end
$var wire 1 q AddSub $end
$var wire 16 r g [15:0] $end
$var wire 16 s p [15:0] $end
$var wire 16 t q [15:0] $end
$var wire 16 u xor_out [15:0] $end
$var wire 16 v sub_out [15:0] $end
$var wire 16 w or_out [15:0] $end
$var wire 16 x mod_out [15:0] $end
$var wire 7 y math_out [6:0] $end
$var wire 16 z divide_out [15:0] $end
$var wire 16 { and_out [15:0] $end
$var wire 16 | add_out [15:0] $end
$scope module addme $end
$var wire 16 } a [15:0] $end
$var wire 1 q addsub $end
$var wire 16 ~ b [15:0] $end
$var wire 1 !" t $end
$var wire 16 "" out [15:0] $end
$upscope $end
$scope module addtri $end
$var wire 16 #" a [15:0] $end
$var wire 1 $" enable $end
$var reg 16 %" b [15:0] $end
$upscope $end
$scope module andme $end
$var wire 16 &" a [15:0] $end
$var wire 16 '" b [15:0] $end
$var wire 16 (" g [15:0] $end
$upscope $end
$scope module andtri $end
$var wire 16 )" a [15:0] $end
$var wire 1 *" enable $end
$var reg 16 +" b [15:0] $end
$upscope $end
$scope module divme $end
$var wire 16 ," dividend [15:0] $end
$var wire 16 -" divisor [15:0] $end
$var wire 16 ." remainder [15:0] $end
$var wire 16 /" quotient [15:0] $end
$upscope $end
$scope module divtri $end
$var wire 16 0" a [15:0] $end
$var wire 1 1" enable $end
$var reg 16 2" b [15:0] $end
$upscope $end
$scope module modtri $end
$var wire 16 3" a [15:0] $end
$var wire 1 4" enable $end
$var reg 16 5" b [15:0] $end
$upscope $end
$scope module my_xor $end
$var wire 16 6" a [15:0] $end
$var wire 16 7" b [15:0] $end
$var wire 16 8" g [15:0] $end
$upscope $end
$scope module orme $end
$var wire 16 9" a [15:0] $end
$var wire 16 :" b [15:0] $end
$var wire 16 ;" g [15:0] $end
$upscope $end
$scope module ortri $end
$var wire 16 <" a [15:0] $end
$var wire 1 =" enable $end
$var reg 16 >" b [15:0] $end
$upscope $end
$scope module subme $end
$var wire 16 ?" a [15:0] $end
$var wire 16 @" b [15:0] $end
$var wire 16 A" out [15:0] $end
$upscope $end
$scope module subtri $end
$var wire 16 B" a [15:0] $end
$var wire 1 C" enable $end
$var reg 16 D" b [15:0] $end
$upscope $end
$scope module xortri $end
$var wire 16 E" a [15:0] $end
$var wire 1 F" enable $end
$var reg 16 G" b [15:0] $end
$upscope $end
$upscope $end
$scope module cc $end
$var wire 1 6 clk $end
$var wire 4 H" func [3:0] $end
$var wire 16 I" input1 [15:0] $end
$var wire 16 J" input2 [15:0] $end
$var wire 8 K" temp2 [7:0] $end
$var wire 8 L" temp1 [7:0] $end
$var wire 9 M" temp [8:0] $end
$var wire 5 N" current_state [4:0] $end
$var reg 1 5 AddSub $end
$var reg 8 O" R_in [7:0] $end
$var reg 8 P" R_out [7:0] $end
$var reg 1 4 a_in $end
$var reg 1 1 data_out $end
$var reg 1 0 g_in $end
$var reg 1 / g_out $end
$var reg 7 Q" math_enables [6:0] $end
$var reg 5 R" next_state [4:0] $end
$scope module in1 $end
$var wire 1 6 clk $end
$var wire 16 S" reg_num [15:0] $end
$var reg 8 T" reg_enable [7:0] $end
$upscope $end
$scope module in2 $end
$var wire 1 6 clk $end
$var wire 16 U" reg_num [15:0] $end
$var reg 8 V" reg_enable [7:0] $end
$upscope $end
$upscope $end
$scope module g_buf $end
$var wire 16 W" a [15:0] $end
$var wire 1 / enable $end
$var reg 16 X" b [15:0] $end
$upscope $end
$upscope $end
$enddefinitions $end
#0
$dumpvars
b0zzz X"
bx W"
b100 V"
b101 U"
b10000000 T"
b0 S"
b0 R"
b0 Q"
b0 P"
b0 O"
b0 N"
b100000 M"
b10000000 L"
b100 K"
b101 J"
b0 I"
b1 H"
b0zzz G"
0F"
bx E"
b0zzz D"
0C"
bx B"
bx A"
b0zzz @"
bx ?"
b0zzz >"
0="
bx <"
bx ;"
b0zzz :"
bx 9"
bx 8"
b0zzz 7"
bx 6"
b0zzz 5"
04"
bx 3"
b0zzz 2"
01"
bx 0"
bx /"
bx ."
b0zzz -"
bx ,"
b0zzz +"
0*"
b0xxx )"
b0xxx ("
b0zzz '"
bx &"
b0zzz %"
0$"
bx #"
bx ""
0!"
b0zzz ~
bx }
bx |
b0xxx {
bx z
b0 y
bx x
bx w
bx v
bx u
b0zzz t
bx s
b0zzz r
zq
b0zzz p
0o
bx n
b0zzz m
0l
bx k
b0zzz j
0i
bx h
b0zzz g
0f
bx e
b0zzz d
0c
bx b
b0zzz a
0`
bx _
b0zzz ^
0]
bx \
b0zzz [
0Z
bx Y
bx X
b0zzz W
0V
bx U
b0zzz T
0S
bx R
b0zzz Q
0P
bx O
b0zzz N
0M
bx L
b0zzz K
0J
bx I
b0zzz H
0G
bx F
b0zzz E
0D
bx C
b0zzz B
0A
bx @
b0zzz ?
b0zzz >
b101 =
bx <
b0zzz ;
b101 :
b0 9
b1 8
b0 7
16
05
04
bx 3
b0 2
01
00
0/
b0 .
b0 -
b0 ,
bx +
bx *
bx )
bx (
bx '
bx &
bx %
bx $
bx #
b0zzz "
b0zzz !
$end
#50000
b101 +
b101 C
b101 Y
b0x0x {
b0x0x ("
b0x0x )"
bx1x1 w
bx1x1 ;"
bx1x1 <"
1A
b101 !
b101 ;
b101 B
b101 E
b101 H
b101 K
b101 N
b101 Q
b101 T
b101 W
b101 t
b101 ~
b101 '"
b101 -"
b101 7"
b101 :"
b101 @"
b101 >
b10000000 -
b10000000 O"
11
b100001 M"
b1 2
b1 N"
b1 R"
06
b1 7
#100000
0A
b0 -
b0 O"
b0xxx {
b0xxx ("
b0xxx )"
bx w
bx ;"
bx <"
b0zzz !
b0zzz ;
b0zzz B
b0zzz E
b0zzz H
b0zzz K
b0zzz N
b0zzz Q
b0zzz T
b0zzz W
b0zzz t
b0zzz ~
b0zzz '"
b0zzz -"
b0zzz 7"
b0zzz :"
b0zzz @"
b0zzz >
01
b100000 M"
b0 2
b0 N"
b0 R"
b1000 L"
b1000 T"
b100 9
b100 I"
b100 S"
16
b10 7
#150000
b101 '
b101 O
b101 e
b0x0x {
b0x0x ("
b0x0x )"
bx1x1 w
bx1x1 ;"
bx1x1 <"
1M
b101 !
b101 ;
b101 B
b101 E
b101 H
b101 K
b101 N
b101 Q
b101 T
b101 W
b101 t
b101 ~
b101 '"
b101 -"
b101 7"
b101 :"
b101 @"
b101 >
b1000 -
b1000 O"
11
b100001 M"
b1 2
b1 N"
b1 R"
06
b11 7
#200000
0M
b0 -
b0 O"
b0xxx {
b0xxx ("
b0xxx )"
bx w
bx ;"
bx <"
b0zzz !
b0zzz ;
b0zzz B
b0zzz E
b0zzz H
b0zzz K
b0zzz N
b0zzz Q
b0zzz T
b0zzz W
b0zzz t
b0zzz ~
b0zzz '"
b0zzz -"
b0zzz 7"
b0zzz :"
b0zzz @"
b0zzz >
01
b100000 M"
b0 2
b0 N"
b0 R"
b1000 K"
b1000 V"
b100000 L"
b100000 T"
b100 :
b100 =
b100 J"
b100 U"
b10 9
b10 I"
b10 S"
16
b100 7
#250000
b100 )
b100 I
b100 _
b0x00 {
b0x00 ("
b0x00 )"
bx1xx w
bx1xx ;"
bx1xx <"
1G
b100 !
b100 ;
b100 B
b100 E
b100 H
b100 K
b100 N
b100 Q
b100 T
b100 W
b100 t
b100 ~
b100 '"
b100 -"
b100 7"
b100 :"
b100 @"
b100 >
b100000 -
b100000 O"
11
b100001 M"
b1 2
b1 N"
b1 R"
06
b101 7
#300000
0G
b0 -
b0 O"
b0xxx {
b0xxx ("
b0xxx )"
bx w
bx ;"
bx <"
b0zzz !
b0zzz ;
b0zzz B
b0zzz E
b0zzz H
b0zzz K
b0zzz N
b0zzz Q
b0zzz T
b0zzz W
b0zzz t
b0zzz ~
b0zzz '"
b0zzz -"
b0zzz 7"
b0zzz :"
b0zzz @"
b0zzz >
01
b100000 M"
b0 2
b0 N"
b0 R"
b1000000 K"
b1000000 V"
b100 L"
b100 T"
b1 :
b1 =
b1 J"
b1 U"
b101 9
b101 I"
b101 S"
16
b110 7
#350000
b1 &
b1 R
b1 h
b0x {
b0x ("
b0x )"
bx1 w
bx1 ;"
bx1 <"
1P
b1 !
b1 ;
b1 B
b1 E
b1 H
b1 K
b1 N
b1 Q
b1 T
b1 W
b1 t
b1 ~
b1 '"
b1 -"
b1 7"
b1 :"
b1 @"
b1 >
b100 -
b100 O"
11
b100001 M"
b1 2
b1 N"
b1 R"
06
b111 7
#400000
0P
b0 -
b0 O"
b0xxx {
b0xxx ("
b0xxx )"
bx w
bx ;"
bx <"
b0zzz !
b0zzz ;
b0zzz B
b0zzz E
b0zzz H
b0zzz K
b0zzz N
b0zzz Q
b0zzz T
b0zzz W
b0zzz t
b0zzz ~
b0zzz '"
b0zzz -"
b0zzz 7"
b0zzz :"
b0zzz @"
b0zzz >
01
b0 2
b0 N"
b0 R"
b100 K"
b100 V"
b10000000 L"
b10000000 T"
b101 :
b101 =
b101 J"
b101 U"
b0 9
b0 I"
b0 S"
b1000000 M"
b10 8
b10 H"
16
b1000 7
#450000
b0zzz +
b0zzz C
b0zzz Y
b0x {
b0x ("
b0x )"
bx1 w
bx1 ;"
bx1 <"
b1 !
b1 ;
b1 B
b1 E
b1 H
b1 K
b1 N
b1 Q
b1 T
b1 W
b1 t
b1 ~
b1 '"
b1 -"
b1 7"
b1 :"
b1 @"
b1 j
1i
1A
b100 ,
b100 P"
b10000000 -
b10000000 O"
b1000010 M"
b10 2
b10 N"
b10 R"
06
b1001 7
#500000
b0xxx {
b0xxx ("
b0xxx )"
bx w
bx ;"
bx <"
b0zzz !
b0zzz ;
b0zzz B
b0zzz E
b0zzz H
b0zzz K
b0zzz N
b0zzz Q
b0zzz T
b0zzz W
b0zzz t
b0zzz ~
b0zzz '"
b0zzz -"
b0zzz 7"
b0zzz :"
b0zzz @"
b0zzz j
0i
0A
b1 +
b1 C
b1 Y
b0 ,
b0 P"
b0 -
b0 O"
b1000000 M"
b0 2
b0 N"
b0 R"
b10000000 K"
b10000000 V"
b100000 L"
b100000 T"
b0 :
b0 =
b0 J"
b0 U"
b10 9
b10 I"
b10 S"
16
b1010 7
#550000
b0zzz )
b0zzz I
b0zzz _
b0x {
b0x ("
b0x )"
bx1 w
bx1 ;"
bx1 <"
b1 !
b1 ;
b1 B
b1 E
b1 H
b1 K
b1 N
b1 Q
b1 T
b1 W
b1 t
b1 ~
b1 '"
b1 -"
b1 7"
b1 :"
b1 @"
b1 [
1Z
1G
b10000000 ,
b10000000 P"
b100000 -
b100000 O"
b1000010 M"
b10 2
b10 N"
b10 R"
06
b1011 7
#600000
b0xxx {
b0xxx ("
b0xxx )"
bx w
bx ;"
bx <"
b0zzz !
b0zzz ;
b0zzz B
b0zzz E
b0zzz H
b0zzz K
b0zzz N
b0zzz Q
b0zzz T
b0zzz W
b0zzz t
b0zzz ~
b0zzz '"
b0zzz -"
b0zzz 7"
b0zzz :"
b0zzz @"
b0zzz [
0Z
0G
b1 )
b1 I
b1 _
b0 ,
b0 P"
b0 -
b0 O"
b0 2
b0 N"
b0 R"
b100 K"
b100 V"
b10000000 L"
b10000000 T"
b101 :
b101 =
b101 J"
b101 U"
b0 9
b0 I"
b0 S"
b100100000 M"
b1001 8
b1001 H"
16
b1100 7
#650000
b0xxx u
b0xxx 8"
b0xxx E"
b0zzz 3
b0zzz <
b0zzz s
b0zzz }
b0zzz &"
b0zzz ,"
b0zzz 6"
b0zzz 9"
b0zzz ?"
b0x {
b0x ("
b0x )"
b0xx1 w
b0xx1 ;"
b0xx1 <"
bx "
bx ?
bx r
bx 5"
b1 !
b1 ;
b1 B
b1 E
b1 H
b1 K
b1 N
b1 Q
b1 T
b1 W
b1 t
b1 ~
b1 '"
b1 -"
b1 7"
b1 :"
b1 @"
b1 [
14"
1Z
b1 .
b1 y
b1 Q"
14
b10000000 ,
b10000000 P"
b100110110 M"
b10110 2
b10110 N"
b10110 R"
06
b1101 7
#700000
b1 {
b1 ("
b1 )"
b0 "
b0 ?
b0 r
b0 5"
b0 u
b0 8"
b0 E"
b1 w
b1 ;"
b1 <"
b10 |
b10 ""
b10 #"
b1 z
b1 /"
b1 0"
b0 x
b0 ."
b0 3"
b0 v
b0 A"
b0 B"
b1 3
b1 <
b1 s
b1 }
b1 &"
b1 ,"
b1 6"
b1 9"
b1 ?"
b1 j
b1 !
b1 ;
b1 B
b1 E
b1 H
b1 K
b1 N
b1 Q
b1 T
b1 W
b1 t
b1 ~
b1 '"
b1 -"
b1 7"
b1 :"
b1 @"
b0zzz [
1i
0Z
10
b100 ,
b100 P"
b100110111 M"
b10111 2
b10111 N"
b10111 R"
16
b1110 7
