register.v
module register(x, clk, enable, y);
    //4-bit register
    //given in lecture 10 - modified
    input [2:0] x;
    input clk, enable;
    output reg [2:0] y;

    always @(clk or  enable) begin
        if (enable == 1'b1)
            y <= x; 
        
    end

endmodule

tri_buf.v
module tri_buf(a, b, enable);
    input [2:0] a; //bits based on in and out
    input enable;
    output reg [2:0] b;

    always @(enable or a) begin
        if  (enable) begin
            b = a;
        end else begin
            b = 3'bzzz;
        end
    end

endmodule

reg_decoder.v
module reg_decoder(reg_num, clk, reg_enable);
    input clk;
    input [2:0] reg_num;
    output reg [3:0] reg_enable; //8 registers

    always @(clk) begin
        case(reg_num)
            3'b000 : reg_enable = 4'b1000; //0000; 
            3'b001 : reg_enable = 4'b0100; //0000;
            3'b010 : reg_enable = 4'b0010; //0000;
            3'b011 : reg_enable = 4'b0001; //0000;
            // 3'b100 : reg_enable = 8'b00001000; 
            // 3'b101 : reg_enable = 8'b00000100;
            // 3'b110 : reg_enable = 8'b00000010;
            // 3'b111 : reg_enable = 8'b00000001;
            default : reg_enable = 4'b0000; //0000; end
        endcase
    end
endmodule

state_machine.v
module state_machine (input1, input2, current_state, func, clk, next_state, data_out, R_in, R_out, AddSub, Rh_in, Rl_in, Rl_out, AS_enable, XOR_enable, sel);
    input clk;
    input [2:0] input1, input2;
    input [3:0] func;
    input [4:0] current_state; 
    output reg [4:0] next_state;
    output reg data_out, AddSub, Rh_in, Rl_in, Rl_out, AS_enable, XOR_enable;
    output reg [3:0] R_out, R_in;
    output reg [1:0] sel;
    wire [3:0] temp1, temp2;
    wire [8:0] temp;

    
    assign temp = {func, current_state};

    reg_decoder in1(.reg_num(input1), .clk(clk), .reg_enable(temp1));
    reg_decoder in2(.reg_num(input2), .clk(clk), .reg_enable(temp2));

    


    always @ (clk) begin
        case(temp)
            9'b000100000 : begin next_state = 5'b00001; data_out = 1'b1; R_in = temp1; R_out = 4'b0000; AddSub = 1'b0; Rh_in = 1'b0;   Rl_in = 1'b0; Rl_out = 1'b0; AS_enable = 1'b0; XOR_enable = 1'b0; end
            9'b001000000 : begin next_state = 5'b00010; data_out = 1'b0; R_in = temp1; R_out = temp2;  AddSub = 1'b0; Rh_in = 1'b0;   Rl_in = 1'b0; Rl_out = 1'b0; AS_enable = 1'b0; XOR_enable = 1'b0; end
            9'b001100000 : begin next_state = 5'b00011; data_out = 1'b0; R_in = 4'b0000;R_out = temp1;  AddSub = 1'b0; Rh_in = 1'b1;   Rl_in = 1'b0; Rl_out = 1'b0; AS_enable = 1'b1; XOR_enable = 1'b0; sel = 2'b00; end
            9'b001100011 : begin next_state = 5'b00100; data_out = 1'b0; R_in = 4'b0000;R_out = temp2;  AddSub = 1'b0; Rh_in = 1'b0;   Rl_in = 1'b1; Rl_out = 1'b0; AS_enable = 1'b1; XOR_enable = 1'b0; sel = 2'b00; end
            9'b001100100 : begin next_state = 5'b00101; data_out = 1'b0; R_in = temp1; R_out = 4'b0000; AddSub = 1'b0; Rh_in = 1'b0;   Rl_in = 1'b0; Rl_out = 1'b1; AS_enable = 1'b1; XOR_enable = 1'b0; sel = 2'b00; end
            9'b010000000 : begin next_state = 5'b00111; data_out = 1'b0; R_in = 4'b0000;R_out = temp1;  AddSub = 1'b1; Rh_in = 1'b1;   Rl_in = 1'b0; Rl_out = 1'b0; AS_enable = 1'b1; XOR_enable = 1'b0; sel = 2'b01; end
            9'b010000111 : begin next_state = 5'b01000; data_out = 1'b0; R_in = 4'b0000;R_out = temp2;  AddSub = 1'b1; Rh_in = 1'b0;   Rl_in = 1'b1; Rl_out = 1'b0; AS_enable = 1'b1; XOR_enable = 1'b0; sel = 2'b01; end
            9'b010001000 : begin next_state = 5'b01001; data_out = 1'b0; R_in = temp1; R_out = 4'b0000; AddSub = 1'b1; Rh_in = 1'b0;   Rl_in = 1'b0; Rl_out = 1'b1; AS_enable = 1'b1; XOR_enable = 1'b0; sel = 2'b01; end
            9'b010100000 : begin next_state = 5'b01010; data_out = 1'b0; R_in = 4'b0000;R_out = temp1;  AddSub = 1'b0; Rh_in = 1'b1;   Rl_in = 1'b0; Rl_out = 1'b0; AS_enable = 1'b0; XOR_enable = 1'b1; sel = 2'b10; end
            9'b010101010 : begin next_state = 5'b01011; data_out = 1'b0; R_in = 4'b0000;R_out = temp2;  AddSub = 1'b0; Rh_in = 1'b0;   Rl_in = 1'b1; Rl_out = 1'b0; AS_enable = 1'b0; XOR_enable = 1'b1; sel = 2'b10; end
            9'b010101011 : begin next_state = 5'b01100; data_out = 1'b0; R_in = 4'b0000;R_out = 4'b0000; AddSub = 1'b0; Rh_in = 1'b0;   Rl_in = 1'b0; Rl_out = 1'b1; AS_enable = 1'b0; XOR_enable = 1'b1; sel = 2'b10; end
            
            default begin next_state = 5'b00000; data_out = 1'b0; R_in <= 4'b0000;R_out <= 4'b0000; AddSub = 1'b0; Rh_in = 1'b0;   Rl_in = 1'b0; Rl_out = 1'b0; AS_enable = 1'b0; XOR_enable = 1'b0; end
        endcase
    end
endmodule

test_TB.v
`timescale 1ns / 1ps
 
module test_TB;

	reg [2:0] in1, in2;
	wire [2:0] bus, t1, t2, t3, t4, t5, t6, t7, t8, temp, a_out, temp1, alu_out,  xor_out, add_out, sub_out, g;
	reg clk;
	reg [3:0] func;
	wire data_out, a_in, g_out, g_in,  AddSub, AS_enable, XOR_enable;
	reg [4:0] count;
	wire [3:0] reg_in, reg_out;
	wire [4:0] current_state;




	state_machine cc(.current_state(current_state), .input1(in1), .input2(in2), .func(func), .clk(clk), .next_state(current_state), .data_out(data_out), .R_in(reg_in), .R_out(reg_out), .AddSub(AddSub), .Rh_in(a_in), .Rl_in(g_in), .Rl_out(g_out), .AS_enable(AS_enable), .XOR_enable(XOR_enable));
	// my_fsm f1(.func(func), .clk(clk), .reg_enable(reg_enable), .buf_enable(buf_enable), .input1(a), .input2(b), .en_D(en_D), .g_buf_en(gbuf_en), .en_A(en_A), .g_en(G_en));
	tri_buf D(.a(in2), .enable(data_out), .b(bus));

	// register R0(.x(bus), .clk(clk), .enable(reg_in[7]), .y(t1));
	// register R1(.x(bus), .clk(clk), .enable(reg_in[6]), .y(t2));
	// register R2(.x(bus), .clk(clk), .enable(reg_in[5]), .y(t3));
	// register R3(.x(bus), .clk(clk), .enable(reg_in[4]), .y(t4));
	register R4(.x(bus), .clk(clk), .enable(reg_in[3]), .y(t5));
	register R5(.x(bus), .clk(clk), .enable(reg_in[2]), .y(t6));
	register R6(.x(bus), .clk(clk), .enable(reg_in[1]), .y(t7));
	register R7(.x(bus), .clk(clk), .enable(reg_in[0]), .y(t8));

	// tri_buf T0(.a(t1), .enable(reg_out[7]), .b(bus));
 	// tri_buf T1(.a(t2), .enable(reg_out[6]), .b(bus));
	// tri_buf T2(.a(t3), .enable(reg_out[5]), .b(bus));
	// tri_buf T3(.a(t4), .enable(reg_out[4]), .b(bus));
	tri_buf T4(.a(t5), .enable(reg_out[3]), .b(bus));
 	tri_buf T5(.a(t6), .enable(reg_out[2]), .b(bus));
	tri_buf T6(.a(t7), .enable(reg_out[1]), .b(bus));
	tri_buf T7(.a(t8), .enable(reg_out[0]), .b(bus));

	register A(.x(bus), .clk(clk), .enable(a_in), .y(a_out));
	// xor_function my_xor(.a(a_out), .b(bus), .g(xor_out));
	// adding addme(.a(a_out), .b(bus), .addsub(AddSub), .out(add_out));
	// subbing subme(.a(a_out), .b(bus), .out(sub_out));
	// mux mymux(.a(xor_out), .b(add_out), .c(sub_out), .out(g));
	// register G(.x(g), .clk(clk), .enable(g_in), .y(temp1));
	// tri_buf G_buf(.a(temp1), .enable(g_out), .b(bus));

	// register A(.x(bus), .clk(clk), .enable(a_in), .y(a_out));
	// my_alu ALU(.p(a_out), .q(bus), .addsub(AddSub), .XOR_enable(XOR_enable), .r(alu_out));
	// register G(.x(alu_out), .clk(clk), .enable(g_in), .y(temp1));
	// tri_buf G_buf(.a(temp1), .enable(g_out), .b(bus));

	




	initial begin 
		count = 5'b00000;
	end
	
	always begin
		#50
		count=count+5'b00001;
	end

	
	
	always @(*) begin
		case (count)
		5'b00000 : begin func = 4'b0001; in1 = 3'b000; in2 = 3'b011;  clk = 1;     end
		5'b00001 : begin func = 4'b0001; in1 = 3'b000; in2 = 3'b011;  clk = 0;    end
		5'b00010 : begin func = 4'b0001; in1 = 3'b000; in2 = 3'b011;  clk = 1;     end
        5'b00011 : begin func = 4'b0001; in1 = 3'b001; in2 = 3'b101;  clk = 1;     end

        5'b00100 : begin func = 4'b0001;  in1 = 3'b001; in2 = 3'b101;  clk = 0;     end
		5'b00101 : begin func = 4'b0001;  in1 = 3'b001; in2 = 3'b101;  clk = 1;    end
		5'b00110 : begin func = 4'b0001;  in1 = 3'b010; in2 = 3'b110;  clk = 1;     end
        5'b00111 : begin func = 4'b0001;  in1 = 3'b010; in2 = 3'b110;  clk = 0;     end

		5'b01000 : begin func = 4'b0001;  in1 = 3'b010; in2 = 3'b110;  clk = 1;     end
		5'b01001 : begin func = 4'b0001;  in1 = 3'b011; in2 = 3'b001;  clk = 1;    end
		5'b01010 : begin func = 4'b0001;  in1 = 3'b011; in2 = 3'b001;  clk = 0;     end
        5'b01011 : begin func = 4'b0001;  in1 = 3'b011; in2 = 3'b001;  clk = 1;     end

		5'b01100 : begin func = 4'b0001;  in1 = 3'b100; in2 = 3'b000;  clk = 1;     end
		5'b01101 : begin func = 4'b0001;  in1 = 3'b100; in2 = 3'b000;  clk = 0;    end
		5'b01110 : begin func = 4'b0001;  in1 = 3'b100; in2 = 3'b000;  clk = 1;     end
        5'b01111 : begin func = 4'b0001;  in1 = 3'b101; in2 = 3'b001;  clk = 1;     end


		default : func = 4'b0000;
        

	endcase
end

	initial begin
		$dumpfile("test_TB.vcd");
		$dumpvars(0, test_TB);
		#1000
		$finish;
	end
 
endmodule

test_TB.vcd
$date
	Sun May 21 19:48:16 2023
$end
$version
	Icarus Verilog
$end
$timescale
	1ps
$end
$scope module test_TB $end
$var wire 3 ! bus [2:0] $end
$var wire 3 " t8 [2:0] $end
$var wire 3 # t7 [2:0] $end
$var wire 3 $ t6 [2:0] $end
$var wire 3 % t5 [2:0] $end
$var wire 4 & reg_out [3:0] $end
$var wire 4 ' reg_in [3:0] $end
$var wire 1 ( g_out $end
$var wire 1 ) g_in $end
$var wire 1 * data_out $end
$var wire 5 + current_state [4:0] $end
$var wire 3 , a_out [2:0] $end
$var wire 1 - a_in $end
$var wire 1 . XOR_enable $end
$var wire 1 / AddSub $end
$var wire 1 0 AS_enable $end
$var reg 1 1 clk $end
$var reg 5 2 count [4:0] $end
$var reg 4 3 func [3:0] $end
$var reg 3 4 in1 [2:0] $end
$var reg 3 5 in2 [2:0] $end
$scope module A $end
$var wire 1 1 clk $end
$var wire 3 6 x [2:0] $end
$var wire 1 - enable $end
$var reg 3 7 y [2:0] $end
$upscope $end
$scope module D $end
$var wire 3 8 a [2:0] $end
$var wire 1 * enable $end
$var reg 3 9 b [2:0] $end
$upscope $end
$scope module R4 $end
$var wire 1 1 clk $end
$var wire 1 : enable $end
$var wire 3 ; x [2:0] $end
$var reg 3 < y [2:0] $end
$upscope $end
$scope module R5 $end
$var wire 1 1 clk $end
$var wire 1 = enable $end
$var wire 3 > x [2:0] $end
$var reg 3 ? y [2:0] $end
$upscope $end
$scope module R6 $end
$var wire 1 1 clk $end
$var wire 1 @ enable $end
$var wire 3 A x [2:0] $end
$var reg 3 B y [2:0] $end
$upscope $end
$scope module R7 $end
$var wire 1 1 clk $end
$var wire 1 C enable $end
$var wire 3 D x [2:0] $end
$var reg 3 E y [2:0] $end
$upscope $end
$scope module T4 $end
$var wire 3 F a [2:0] $end
$var wire 1 G enable $end
$var reg 3 H b [2:0] $end
$upscope $end
$scope module T5 $end
$var wire 3 I a [2:0] $end
$var wire 1 J enable $end
$var reg 3 K b [2:0] $end
$upscope $end
$scope module T6 $end
$var wire 3 L a [2:0] $end
$var wire 1 M enable $end
$var reg 3 N b [2:0] $end
$upscope $end
$scope module T7 $end
$var wire 3 O a [2:0] $end
$var wire 1 P enable $end
$var reg 3 Q b [2:0] $end
$upscope $end
$scope module cc $end
$var wire 1 1 clk $end
$var wire 4 R func [3:0] $end
$var wire 3 S input1 [2:0] $end
$var wire 3 T input2 [2:0] $end
$var wire 4 U temp2 [3:0] $end
$var wire 4 V temp1 [3:0] $end
$var wire 9 W temp [8:0] $end
$var wire 5 X current_state [4:0] $end
$var reg 1 0 AS_enable $end
$var reg 1 / AddSub $end
$var reg 4 Y R_in [3:0] $end
$var reg 4 Z R_out [3:0] $end
$var reg 1 - Rh_in $end
$var reg 1 ) Rl_in $end
$var reg 1 ( Rl_out $end
$var reg 1 . XOR_enable $end
$var reg 1 * data_out $end
$var reg 5 [ next_state [4:0] $end
$var reg 2 \ sel [1:0] $end
$scope module in1 $end
$var wire 1 1 clk $end
$var wire 3 ] reg_num [2:0] $end
$var reg 4 ^ reg_enable [3:0] $end
$upscope $end
$scope module in2 $end
$var wire 1 1 clk $end
$var wire 3 _ reg_num [2:0] $end
$var reg 4 ` reg_enable [3:0] $end
$upscope $end
$upscope $end
$upscope $end
$enddefinitions $end
#0
$dumpvars
b1 `
b11 _
b1000 ^
b0 ]
bx \
b0 [
b0 Z
b0 Y
b0 X
b100000 W
b1000 V
b1 U
b11 T
b0 S
b1 R
bz Q
0P
bx O
bz N
0M
bx L
bz K
0J
bx I
bz H
0G
bx F
bx E
bz D
0C
bx B
bz A
0@
bx ?
bz >
0=
bx <
bz ;
0:
bz 9
b11 8
bx 7
bz 6
b11 5
b0 4
b1 3
b0 2
11
00
0/
0.
0-
bx ,
b0 +
0*
0)
0(
b0 '
b0 &
bx %
bx $
bx #
bx "
bz !
$end
#50000
b11 %
b11 <
b11 F
1:
b11 !
b11 6
b11 ;
b11 >
b11 A
b11 D
b11 9
b1000 '
b1000 Y
1*
b100001 W
b1 +
b1 X
b1 [
01
b1 2
#100000
0:
b0 '
b0 Y
bz !
bz 6
bz ;
bz >
bz A
bz D
bz 9
0*
b100000 W
b0 +
b0 X
b0 [
11
b10 2
#150000
b101 5
b101 8
b101 T
b101 _
b1 4
b1 S
b1 ]
b11 2
#200000
b101 %
b101 <
b101 F
1:
b101 !
b101 6
b101 ;
b101 >
b101 A
b101 D
b101 9
b100 V
b100 ^
b0 U
b0 `
b1000 '
b1000 Y
1*
b100001 W
b1 +
b1 X
b1 [
01
b100 2
#250000
0:
b0 '
b0 Y
bz !
bz 6
bz ;
bz >
bz A
bz D
bz 9
0*
b100000 W
b0 +
b0 X
b0 [
11
b101 2
#300000
b110 5
b110 8
b110 T
b110 _
b10 4
b10 S
b10 ]
b110 2
#350000
b110 $
b110 ?
b110 I
1=
b110 !
b110 6
b110 ;
b110 >
b110 A
b110 D
b110 9
b10 V
b10 ^
b100 '
b100 Y
1*
b100001 W
b1 +
b1 X
b1 [
01
b111 2
#400000
0=
b0 '
b0 Y
bz !
bz 6
bz ;
bz >
bz A
bz D
bz 9
0*
b100000 W
b0 +
b0 X
b0 [
11
b1000 2
#450000
b1 5
b1 8
b1 T
b1 _
b11 4
b11 S
b11 ]
b1001 2
#500000
b1 #
b1 B
b1 L
1@
b1 !
b1 6
b1 ;
b1 >
b1 A
b1 D
b1 9
b1 V
b1 ^
b100 U
b100 `
b10 '
b10 Y
1*
b100001 W
b1 +
b1 X
b1 [
01
b1010 2
#550000
0@
b0 '
b0 Y
bz !
bz 6
bz ;
bz >
bz A
bz D
bz 9
0*
b100000 W
b0 +
b0 X
b0 [
11
b1011 2
#600000
b0 5
b0 8
b0 T
b0 _
b100 4
b100 S
b100 ]
b1100 2
#650000
b0 "
b0 E
b0 O
1C
b0 !
b0 6
b0 ;
b0 >
b0 A
b0 D
b0 9
b0 V
b0 ^
b1000 U
b1000 `
b1 '
b1 Y
1*
b100001 W
b1 +
b1 X
b1 [
01
b1101 2
#700000
0C
b0 '
b0 Y
bz !
bz 6
bz ;
bz >
bz A
bz D
bz 9
0*
b100000 W
b0 +
b0 X
b0 [
11
b1110 2
#750000
b1 5
b1 8
b1 T
b1 _
b101 4
b101 S
b101 ]
b1111 2
#800000
b0 W
b0 3
b0 R
b10000 2
#850000
b10001 2
#900000
b10010 2
#950000
b10011 2
#1000000
b10100 2
